cdk_aws_ec2_efs/__init__.py
cdk_aws_ec2_efs/py.typed
cdk_aws_ec2_efs/_jsii/__init__.py
cdk_aws_ec2_efs/_jsii/cdk-aws-ec2-efs@0.0.3.jsii.tgz
cdk_aws_ec2_efs-0.0.3.dist-info/LICENSE
cdk_aws_ec2_efs-0.0.3.dist-info/METADATA
cdk_aws_ec2_efs-0.0.3.dist-info/WHEEL
cdk_aws_ec2_efs-0.0.3.dist-info/top_level.txt
cdk_aws_ec2_efs-0.0.3.dist-info/RECORD
